CHANGELOG.txt
LICENSE.txt
MANIFEST.in
README.txt
setup.py
rand_password_generator/__init__.py
rand_password_generator.egg-info/PKG-INFO
rand_password_generator.egg-info/SOURCES.txt
rand_password_generator.egg-info/dependency_links.txt
rand_password_generator.egg-info/top_level.txt